{"settings": {"tile_size": 16, "map_size": [64, 32]}, "tiles": [{"id": 0, "path": "dirt.png", "type": "tile"}, {"id": 1, "path": "stone.png", "type": "tile"}, {"id": 2, "path": "testimg.png", "type": "object"}, {"id": 3, "path": "testimg.png", "type": "tile"}], "layers": [{"name": "test", "visible": true, "tiles": [{"id": 0, "position": [0.0, 0.0]}, {"id": 1, "position": [16.0, 16.0]}, {"id": 0, "position": [0.0, 16.0]}, {"id": 1, "position": [304.0, 16.0]}, {"id": 1, "position": [304.0, 16.0]}, {"id": 1, "position": [304.0, 32.0]}, {"id": 1, "position": [304.0, 48.0]}, {"id": 1, "position": [304.0, 64.0]}, {"id": 1, "position": [304.0, 80.0]}, {"id": 1, "position": [304.0, 96.0]}, {"id": 1, "position": [304.0, 112.0]}, {"id": 1, "position": [304.0, 128.0]}, {"id": 1, "position": [304.0, 144.0]}, {"id": 1, "position": [304.0, 160.0]}, {"id": 1, "position": [304.0, 176.0]}, {"id": 1, "position": [304.0, 176.0]}, {"id": 1, "position": [304.0, 192.0]}, {"id": 1, "position": [304.0, 208.0]}, {"id": 1, "position": [304.0, 224.0]}, {"id": 1, "position": [288.0, 224.0]}, {"id": 1, "position": [288.0, 224.0]}, {"id": 1, "position": [288.0, 240.0]}, {"id": 1, "position": [272.0, 240.0]}, {"id": 1, "position": [256.0, 240.0]}, {"id": 1, "position": [240.0, 240.0]}, {"id": 1, "position": [224.0, 240.0]}, {"id": 1, "position": [208.0, 240.0]}, {"id": 1, "position": [192.0, 240.0]}, {"id": 1, "position": [176.0, 240.0]}, {"id": 1, "position": [160.0, 240.0]}, {"id": 1, "position": [144.0, 240.0]}, {"id": 1, "position": [128.0, 240.0]}, {"id": 1, "position": [112.0, 240.0]}, {"id": 1, "position": [96.0, 240.0]}, {"id": 1, "position": [80.0, 240.0]}, {"id": 1, "position": [64.0, 240.0]}, {"id": 1, "position": [48.0, 240.0]}, {"id": 1, "position": [32.0, 240.0]}, {"id": 1, "position": [16.0, 240.0]}, {"id": 1, "position": [0.0, 240.0]}, {"id": 1, "position": [0.0, 224.0]}, {"id": 1, "position": [0.0, 208.0]}, {"id": 1, "position": [0.0, 192.0]}, {"id": 1, "position": [0.0, 176.0]}, {"id": 1, "position": [0.0, 160.0]}, {"id": 1, "position": [0.0, 144.0]}, {"id": 1, "position": [0.0, 128.0]}, {"id": 1, "position": [0.0, 112.0]}, {"id": 1, "position": [0.0, 96.0]}, {"id": 1, "position": [0.0, 80.0]}, {"id": 1, "position": [0.0, 64.0]}, {"id": 1, "position": [0.0, 48.0]}, {"id": 1, "position": [0.0, 32.0]}, {"id": 0, "position": [16.0, 0.0]}, {"id": 0, "position": [32.0, 0.0]}, {"id": 0, "position": [48.0, 0.0]}, {"id": 0, "position": [64.0, 0.0]}, {"id": 0, "position": [80.0, 0.0]}, {"id": 0, "position": [96.0, 0.0]}, {"id": 0, "position": [112.0, 0.0]}, {"id": 0, "position": [128.0, 0.0]}, {"id": 0, "position": [144.0, 0.0]}, {"id": 0, "position": [160.0, 0.0]}, {"id": 0, "position": [176.0, 0.0]}, {"id": 0, "position": [192.0, 0.0]}, {"id": 0, "position": [208.0, 0.0]}, {"id": 0, "position": [224.0, 0.0]}, {"id": 0, "position": [240.0, 0.0]}, {"id": 0, "position": [256.0, 0.0]}, {"id": 0, "position": [272.0, 0.0]}, {"id": 0, "position": [288.0, 0.0]}, {"id": 0, "position": [304.0, 0.0]}, {"id": 1, "position": [32.0, 16.0]}, {"id": 1, "position": [48.0, 16.0]}, {"id": 1, "position": [64.0, 16.0]}, {"id": 1, "position": [64.0, 16.0]}, {"id": 1, "position": [80.0, 16.0]}, {"id": 1, "position": [96.0, 16.0]}, {"id": 1, "position": [112.0, 16.0]}, {"id": 1, "position": [112.0, 16.0]}, {"id": 1, "position": [128.0, 16.0]}, {"id": 1, "position": [128.0, 16.0]}, {"id": 1, "position": [144.0, 16.0]}, {"id": 1, "position": [160.0, 16.0]}, {"id": 1, "position": [176.0, 16.0]}, {"id": 1, "position": [192.0, 16.0]}, {"id": 1, "position": [208.0, 16.0]}, {"id": 1, "position": [224.0, 16.0]}, {"id": 1, "position": [240.0, 16.0]}, {"id": 1, "position": [256.0, 16.0]}, {"id": 1, "position": [272.0, 16.0]}, {"id": 1, "position": [288.0, 16.0]}, {"id": 1, "position": [160.0, 32.0]}, {"id": 1, "position": [160.0, 48.0]}, {"id": 1, "position": [160.0, 64.0]}, {"id": 1, "position": [160.0, 80.0]}, {"id": 1, "position": [160.0, 96.0]}, {"id": 1, "position": [160.0, 112.0]}, {"id": 1, "position": [160.0, 112.0]}, {"id": 1, "position": [160.0, 128.0]}, {"id": 1, "position": [160.0, 144.0]}, {"id": 1, "position": [160.0, 160.0]}, {"id": 1, "position": [160.0, 176.0]}, {"id": 1, "position": [160.0, 192.0]}, {"id": 1, "position": [160.0, 208.0]}, {"id": 1, "position": [160.0, 224.0]}, {"id": 1, "position": [16.0, 112.0]}, {"id": 1, "position": [32.0, 112.0]}, {"id": 1, "position": [48.0, 112.0]}, {"id": 1, "position": [64.0, 112.0]}, {"id": 1, "position": [80.0, 112.0]}, {"id": 1, "position": [96.0, 112.0]}, {"id": 1, "position": [128.0, 112.0]}, {"id": 1, "position": [144.0, 112.0]}, {"id": 1, "position": [176.0, 112.0]}, {"id": 1, "position": [192.0, 112.0]}, {"id": 1, "position": [208.0, 112.0]}, {"id": 1, "position": [224.0, 112.0]}, {"id": 1, "position": [240.0, 112.0]}, {"id": 1, "position": [256.0, 112.0]}, {"id": 1, "position": [272.0, 112.0]}, {"id": 1, "position": [288.0, 112.0]}, {"id": 2, "position": [76.0, 76.0]}, {"id": 2, "position": [85.37737083387589, 40.51774072246492]}, {"id": 2, "position": [109.22945834251902, 34.55471884530415]}, {"id": 2, "position": [145.4051243972945, 29.38676655176478]}, {"id": 2, "position": [195.4945081654451, 31.771975302629116]}, {"id": 2, "position": [228.48989588573477, 50.45611051773291]}, {"id": 2, "position": [256.3173313124851, 87.02931136431907]}, {"id": 2, "position": [229.68250026116692, 103.72577262036928]}, {"id": 2, "position": [191.12162545552718, 100.1479594940728]}, {"id": 2, "position": [149.38047231540168, 78.28354594448324]}, {"id": 2, "position": [131.4914066839193, 85.43917219707619]}, {"id": 2, "position": [131.88894147573004, 139.50390388333398]}, {"id": 2, "position": [124.73331522313708, 166.13873493465218]}, {"id": 2, "position": [59.53760936617914, 153.81515638851988]}, {"id": 2, "position": [48.80416998728971, 121.61483825185161]}, {"id": 2, "position": [115.19248021967982, 126.78279054539098]}, {"id": 2, "position": [179.1955817012056, 121.21730346004091]}, {"id": 2, "position": [196.28957774906655, 75.5008024018082]}, {"id": 2, "position": [180.38818607663777, 54.82899322765083]}, {"id": 2, "position": [133.0815458511622, 63.57475864748663]}, {"id": 2, "position": [102.4713668817368, 78.68108073629396]}, {"id": 2, "position": [88.95518396017235, 102.93070303674783]}, {"id": 2, "position": [75.4390010386079, 143.4792518014412]}, {"id": 2, "position": [108.83192355070832, 168.92147847732718]}, {"id": 2, "position": [154.94595940075175, 160.5732478493021]}, {"id": 2, "position": [149.38047231540168, 118.03702512555515]}, {"id": 2, "position": [113.60234105243694, 117.24195554193375]}, {"id": 2, "position": [63.1154224924756, 98.55782032682994]}, {"id": 2, "position": [34.09538269029311, 52.84131926859722]}, {"id": 2, "position": [78.61927937309366, 21.038535923739673]}, {"id": 2, "position": [119.56536292959774, 21.038535923739673]}, {"id": 2, "position": [111.61466709338336, 36.54239280435773]}, {"id": 2, "position": [161.70405086153397, 81.463824278969]}, {"id": 2, "position": [195.0969733736344, 63.57475864748663]}, {"id": 2, "position": [170.44981628136978, 45.685693016004265]}, {"id": 2, "position": [73.45132707955432, 135.13102117341606]}, {"id": 2, "position": [172.4374902404234, 158.5855738902485]}]}, {"name": "mynewlayer", "visible": true, "tiles": [{"id": 0, "position": [48.0, 144.0]}, {"id": 0, "position": [48.0, 144.0]}, {"id": 0, "position": [48.0, 144.0]}, {"id": 0, "position": [48.0, 144.0]}, {"id": 0, "position": [48.0, 144.0]}, {"id": 3, "position": [304.0, 224.0]}, {"id": 3, "position": [288.0, 224.0]}, {"id": 3, "position": [288.0, 224.0]}, {"id": 3, "position": [288.0, 240.0]}, {"id": 3, "position": [272.0, 240.0]}, {"id": 3, "position": [256.0, 240.0]}, {"id": 3, "position": [240.0, 240.0]}, {"id": 3, "position": [224.0, 240.0]}, {"id": 3, "position": [208.0, 240.0]}, {"id": 3, "position": [192.0, 240.0]}, {"id": 3, "position": [176.0, 240.0]}, {"id": 3, "position": [160.0, 240.0]}, {"id": 3, "position": [144.0, 240.0]}, {"id": 3, "position": [128.0, 240.0]}, {"id": 3, "position": [112.0, 240.0]}, {"id": 3, "position": [96.0, 240.0]}, {"id": 3, "position": [80.0, 240.0]}, {"id": 3, "position": [64.0, 240.0]}, {"id": 3, "position": [48.0, 240.0]}, {"id": 3, "position": [32.0, 240.0]}, {"id": 3, "position": [16.0, 240.0]}, {"id": 3, "position": [0.0, 240.0]}, {"id": 3, "position": [0.0, 224.0]}, {"id": 3, "position": [0.0, 208.0]}]}, {"name": "hiddenlayer", "visible": false, "tiles": [{"id": 1, "position": [48.0, 192.0]}, {"id": 1, "position": [48.0, 208.0]}, {"id": 1, "position": [48.0, 208.0]}, {"id": 1, "position": [64.0, 208.0]}, {"id": 1, "position": [64.0, 192.0]}, {"id": 1, "position": [224.0, 192.0]}, {"id": 1, "position": [224.0, 208.0]}, {"id": 1, "position": [224.0, 208.0]}, {"id": 1, "position": [224.0, 208.0]}, {"id": 1, "position": [224.0, 208.0]}, {"id": 1, "position": [224.0, 208.0]}, {"id": 1, "position": [224.0, 208.0]}, {"id": 1, "position": [240.0, 208.0]}, {"id": 1, "position": [240.0, 192.0]}]}]}